django_cloudtask/__init__.py
django_cloudtask/apps.py
django_cloudtask/management/__init__.py
django_cloudtask/management/commands/__init__.py
django_cloudtask/management/commands/sync_scheduler.py
django_cloudtask/task.py
django_cloudtask/urls.py
django_cloudtask/utils.py
django_cloudtask/views.py
django_cloudtask-0.1.5.dist-info/LICENSE
django_cloudtask-0.1.5.dist-info/WHEEL
django_cloudtask-0.1.5.dist-info/METADATA
django_cloudtask-0.1.5.dist-info/RECORD
