Metadata-Version: 2.1
Name: django-cloudtask
Version: 0.1.5
Summary: A django package for managing long running tasks using GCP Cloud Task
Home-page: http://github.com/kogan/
License: BSD-3-Clause
Keywords: django-cloudtask,django,gcp,cloud task
Author: Alec McGavin
Author-email: alec.mcgavin@kogan.com.au
Requires-Python: >=3.6,<4.0
Classifier: Framework :: Django
Classifier: Framework :: Django :: 1.11
Classifier: Framework :: Django :: 2.0
Classifier: Framework :: Django :: 2.1
Classifier: Framework :: Django :: 2.2
Classifier: Intended Audience :: Developers
Classifier: License :: OSI Approved :: BSD License
Classifier: Natural Language :: English
Classifier: Programming Language :: Python
Classifier: Programming Language :: Python :: 3
Classifier: Programming Language :: Python :: 3.6
Classifier: Programming Language :: Python :: 3.7
Classifier: Programming Language :: Python :: 3.8
Requires-Dist: django (>=2.2.12,<3.0.0)
Requires-Dist: django-structlog (>=1.5.2,<2.0.0)
Requires-Dist: google-api-core (>=1.14.2,<2.0.0)
Requires-Dist: google-cloud-scheduler (>=1.3.0,<2.0.0)
Requires-Dist: google-cloud-tasks (>=1.5.0,<2.0.0)
Requires-Dist: structlog (>=20.1.0,<21.0.0)
Project-URL: Documentation, http://github.com/kogan/django-cloudtask/
Project-URL: Repository, http://github.com/kogan/django-cloudtask/
